mypackage/__init__.py
mypackage/file_utils.py
mypackage/math_utils.py
mypackage/string_utils.py
Divyaregu-0.1.3.dist-info/METADATA
Divyaregu-0.1.3.dist-info/WHEEL
Divyaregu-0.1.3.dist-info/top_level.txt
Divyaregu-0.1.3.dist-info/RECORD
